appliapps/__init__.py
applibase-0.0.8.dist-info/DESCRIPTION.rst
applibase-0.0.8.dist-info/METADATA
applibase-0.0.8.dist-info/RECORD
applibase-0.0.8.dist-info/WHEEL
applibase-0.0.8.dist-info/metadata.json
applibase-0.0.8.dist-info/top_level.txt
applicake/__init__.py
applicake/app.py
tests/test_core.py
tests/test_examples.py
tests/test_flow.py
tests/test_workflow.py
