Metadata-Version: 2.0
Name: applibase
Version: 0.0.8
Summary: A framework that simplifies the wrapping of external tools by standardizing input parameters, logging messages and output streams.
Home-page: https://github.com/applicake-tools
Author: ['Lorenz Blum', 'Witold Wolski']
Author-email: ['blum@id.ethz.ch', 'wewolski@gmail.com']
License: BSD
Platform: UNKNOWN
